search_in_youtube_video_comments/__init__.py
search_in_youtube_video_comments/search_in_youtube_video_comments.py
search_in_youtube_video_comments-0.0.2.dist-info/METADATA
search_in_youtube_video_comments-0.0.2.dist-info/WHEEL
search_in_youtube_video_comments-0.0.2.dist-info/entry_points.txt
search_in_youtube_video_comments-0.0.2.dist-info/top_level.txt
search_in_youtube_video_comments-0.0.2.dist-info/RECORD
