Metadata-Version: 2.1
Name: search-in-youtube-video-comments
Version: 0.0.2
Summary: Search in YouTube video comments
Author: Benjamin Loison
Project-URL: Homepage, https://codeberg.org/Benjamin_Loison/Search_in_YouTube_video_comments
Project-URL: Bug Tracker, https://codeberg.org/Benjamin_Loison/Search_in_YouTube_video_comments/issues
Requires-Python: >=3.9
Requires-Dist: requests
